turq/__init__.py
turq/__metadata__.py
turq/editor.py
turq/examples.py
turq/examples.rst
turq/main.py
turq/mock.py
turq/rules.py
turq/editor/editor.css
turq/editor/editor.html.tpl
turq/editor/editor.js
turq/editor/codemirror/addon/runmode/colorize.js
turq/editor/codemirror/addon/runmode/runmode.js
turq/editor/codemirror/lib/codemirror.css
turq/editor/codemirror/lib/codemirror.js
turq/editor/codemirror/mode/python/python.js
turq/util/__init__.py
turq/util/http.py
turq/util/logging.py
turq/util/text.py
turq-0.3.1.dist-info/DESCRIPTION.rst
turq-0.3.1.dist-info/METADATA
turq-0.3.1.dist-info/RECORD
turq-0.3.1.dist-info/WHEEL
turq-0.3.1.dist-info/entry_points.txt
turq-0.3.1.dist-info/metadata.json
turq-0.3.1.dist-info/top_level.txt
