Metadata-Version: 2.0
Name: turq
Version: 0.3.1
Summary: Mock HTTP server
Home-page: https://github.com/vfaronov/turq
Author: Vasiliy Faronov
Author-email: vfaronov@gmail.com
License: ISC
Keywords: HTTP Web server mock mocking test debug
Platform: UNKNOWN
Classifier: Intended Audience :: Developers
Classifier: License :: OSI Approved :: ISC License (ISCL)
Classifier: Programming Language :: Python :: 3 :: Only
Classifier: Programming Language :: Python :: 3.4
Classifier: Programming Language :: Python :: 3.5
Classifier: Programming Language :: Python :: 3.6
Classifier: Topic :: Internet :: WWW/HTTP :: HTTP Servers
Classifier: Topic :: Software Development :: Testing
Classifier: Topic :: Utilities
Requires-Dist: Werkzeug (>=0.12.1)
Requires-Dist: colorlog (>=2.10.0)
Requires-Dist: docutils (>=0.13.1)
Requires-Dist: dominate (>=2.3.1)
Requires-Dist: falcon (>=1.1.0)
Requires-Dist: h11 (>=0.7.0)
Requires-Dist: colorama (>=0.3.7); sys_platform == "win32"
